{
  "version": "5.0.2",
  "flags": {
    "sunglasses": true,
    "half rim": false,
    "rimless": false,
    "mask": false,
    "dark skin": false
  },
  "shapes": [
    {
      "label": "iris",
      "points": [
        [
          879.4,
          888.6
        ],
        [
          875.9,
          891.1
        ],
        [
          872.4,
          892.6
        ],
        [
          868.7,
          893.8
        ],
        [
          864.9,
          894.3
        ],
        [
          861.2,
          894.8
        ],
        [
          857.2,
          894.8
        ],
        [
          853.2,
          894.8
        ],
        [
          849.5,
          894.3
        ],
        [
          845.5,
          893.1
        ],
        [
          842,
          891.6
        ],
        [
          838.8,
          889.6
        ],
        [
          835.8,
          887.1
        ],
        [
          833.1,
          884.1
        ],
        [
          831.3,
          880.6
        ],
        [
          830.4,
          876.9
        ],
        [
          829.9,
          873.2
        ],
        [
          829.9,
          869.2
        ],
        [
          829.9,
          865.2
        ],
        [
          830.6,
          861.5
        ],
        [
          832.1,
          858
        ],
        [
          833.6,
          854.5
        ],
        [
          836.1,
          851.5
        ],
        [
          838.6,
          848.5
        ],
        [
          841.6,
          846
        ],
        [
          845.7,
          844
        ],
        [
          849,
          842.8
        ],
        [
          852.3,
          842.2
        ],
        [
          856.1,
          841.7
        ],
        [
          860,
          841.6
        ],
        [
          864.2,
          841.6
        ],
        [
          867.9,
          841.8
        ],
        [
          871.7,
          842.8
        ],
        [
          875.4,
          844.3
        ],
        [
          878.6,
          846.3
        ],
        [
          881.6,
          848.8
        ],
        [
          884.1,
          852.3
        ],
        [
          885.6,
          855.7
        ],
        [
          886.8,
          859.5
        ],
        [
          887.3,
          863.4
        ],
        [
          887.3,
          867.4
        ],
        [
          886.8,
          871.2
        ],
        [
          885.8,
          874.9
        ],
        [
          884.8,
          878.6
        ],
        [
          883.4,
          882.1
        ],
        [
          881.5,
          885.4
        ]
      ],
      "group_id": null,
      "shape_type": "polygon",
      "flags": {}
    },
    {
      "label": "pupil",
      "points": [
        [
          596.2,
          878
        ],
        [
          595.1,
          879.1
        ],
        [
          593.7,
          879.9
        ],
        [
          592.2,
          880.3
        ],
        [
          590.7,
          880.6
        ],
        [
          589.2,
          880.8
        ],
        [
          587.7,
          880.9
        ],
        [
          586,
          880.9
        ],
        [
          584.5,
          880.7
        ],
        [
          583,
          880.2
        ],
        [
          581.7,
          879.4
        ],
        [
          580.5,
          878.3
        ],
        [
          579.6,
          877.2
        ],
        [
          578.9,
          875.8
        ],
        [
          578.5,
          874.3
        ],
        [
          578.1,
          872.8
        ],
        [
          577.9,
          871.3
        ],
        [
          577.9,
          869.7
        ],
        [
          577.9,
          868.1
        ],
        [
          578.1,
          866.5
        ],
        [
          578.6,
          865
        ],
        [
          579.2,
          863.6
        ],
        [
          580,
          862.3
        ],
        [
          580.9,
          861
        ],
        [
          582,
          859.9
        ],
        [
          583.3,
          859
        ],
        [
          584.8,
          858.3
        ],
        [
          586.3,
          857.8
        ],
        [
          587.8,
          857.4
        ],
        [
          589.3,
          857.3
        ],
        [
          590.8,
          857.5
        ],
        [
          592.3,
          857.8
        ],
        [
          593.7,
          858.4
        ],
        [
          595.2,
          859.2
        ],
        [
          596.5,
          860.1
        ],
        [
          597.6,
          861.2
        ],
        [
          598.4,
          862.5
        ],
        [
          599.2,
          864
        ],
        [
          599.6,
          865.5
        ],
        [
          599.8,
          867.1
        ],
        [
          599.9,
          868.7
        ],
        [
          599.7,
          870.2
        ],
        [
          599.4,
          871.7
        ],
        [
          598.9,
          873.3
        ],
        [
          598.3,
          874.7
        ],
        [
          597.6,
          876.1
        ]
      ],
      "group_id": null,
      "shape_type": "polygon",
      "flags": {}
    },
    {
      "label": "iris",
      "points": [
        [
          611.6,
          880
        ],
        [
          610,
          882.7
        ],
        [
          607.9,
          885.1
        ],
        [
          605.2,
          886.8
        ],
        [
          602.5,
          888.5
        ],
        [
          599.8,
          889.5
        ],
        [
          596.7,
          890.5
        ],
        [
          593.6,
          891.2
        ],
        [
          590.5,
          891.6
        ],
        [
          587.4,
          891.8
        ],
        [
          584.1,
          891.8
        ],
        [
          580.9,
          891.6
        ],
        [
          577.8,
          890.9
        ],
        [
          574.7,
          889.9
        ],
        [
          571.6,
          888.5
        ],
        [
          568.5,
          886.8
        ],
        [
          566,
          884.7
        ],
        [
          563.9,
          882
        ],
        [
          562.5,
          878.9
        ],
        [
          561.5,
          875.8
        ],
        [
          560.6,
          872.7
        ],
        [
          560.4,
          869.6
        ],
        [
          560.4,
          866.3
        ],
        [
          560.8,
          863.2
        ],
        [
          561.9,
          860
        ],
        [
          563.1,
          856.9
        ],
        [
          564.8,
          854
        ],
        [
          566.6,
          851.3
        ],
        [
          569.1,
          849.1
        ],
        [
          571.8,
          847.4
        ],
        [
          574.7,
          845.9
        ],
        [
          577.6,
          844.7
        ],
        [
          580.7,
          843.7
        ],
        [
          584.1,
          843
        ],
        [
          587.4,
          842.6
        ],
        [
          590.9,
          842.6
        ],
        [
          594.4,
          842.6
        ],
        [
          597.5,
          843.1
        ],
        [
          600.6,
          844
        ],
        [
          603.8,
          844.9
        ],
        [
          606.9,
          846.2
        ],
        [
          609.6,
          848
        ],
        [
          611.6,
          850.5
        ],
        [
          613.1,
          853.4
        ],
        [
          614.1,
          856.7
        ],
        [
          614.7,
          860
        ],
        [
          614.9,
          863.4
        ],
        [
          614.9,
          866.7
        ],
        [
          614.7,
          870
        ],
        [
          613.7,
          874.5
        ]
      ],
      "group_id": null,
      "shape_type": "polygon",
      "flags": {}
    },
    {
      "label": "pupil",
      "points": [
        [
          866.1,
          878.9
        ],
        [
          864.8,
          879.8
        ],
        [
          863.4,
          880.5
        ],
        [
          861.9,
          880.9
        ],
        [
          860.3,
          881.2
        ],
        [
          858.7,
          881.3
        ],
        [
          857.1,
          881.3
        ],
        [
          855.4,
          881.3
        ],
        [
          853.9,
          880.9
        ],
        [
          852.5,
          880.2
        ],
        [
          851.1,
          879.4
        ],
        [
          849.9,
          878.4
        ],
        [
          848.8,
          877.3
        ],
        [
          848,
          875.8
        ],
        [
          847.2,
          874.5
        ],
        [
          846.6,
          873.1
        ],
        [
          846.2,
          871.6
        ],
        [
          846.1,
          870.1
        ],
        [
          846.1,
          868.5
        ],
        [
          846.3,
          867
        ],
        [
          846.7,
          865.4
        ],
        [
          847.3,
          864
        ],
        [
          848,
          862.5
        ],
        [
          849,
          861.3
        ],
        [
          850.2,
          860.1
        ],
        [
          851.4,
          859.1
        ],
        [
          852.7,
          858.3
        ],
        [
          854.2,
          857.7
        ],
        [
          855.8,
          857.4
        ],
        [
          857.3,
          857.1
        ],
        [
          858.9,
          857.1
        ],
        [
          860.5,
          857.1
        ],
        [
          862.1,
          857.4
        ],
        [
          863.6,
          857.9
        ],
        [
          865.1,
          858.6
        ],
        [
          866.4,
          859.4
        ],
        [
          867.6,
          860.4
        ],
        [
          868.6,
          861.8
        ],
        [
          869.3,
          863.3
        ],
        [
          869.9,
          864.7
        ],
        [
          870.4,
          866.4
        ],
        [
          870.5,
          868
        ],
        [
          870.6,
          869.5
        ],
        [
          870.6,
          871.1
        ],
        [
          870.5,
          872.6
        ],
        [
          870,
          874.1
        ],
        [
          869.3,
          875.6
        ],
        [
          867.9,
          877.2
        ]
      ],
      "group_id": null,
      "shape_type": "polygon",
      "flags": {}
    }
  ],
  "imagePath": "20231108_120723_717d89f7_IR_LEFT.png",
  "imageData": null,
  "imageHeight": 1600,
  "imageWidth": 1300,
  "annotator": "Daria",
  "MetaData": {
    "SessionID": "20231108_120723_717d89f7",
    "Id": 12574,
    "Distance": 606.061,
    "Stage": 2,
    "ModifiedData": "2023-11-08T12:07:23.4568411",
    "Country": "Italy",
    "SparkUser": "s****a@l****a.com",
    "DeviceSerialNumber": "SP4-0322-0754",
    "SparkMeasurementId": 2158,
    "State": "",
    "CustomerId": "",
    "UID": "717d89f7-2320-47b5-8fe2-6415d33e0e9b",
    "MeasurementData": {
      "Id": 12550,
      "MeasurementId": 12574,
      "Pd": 61.9,
      "MonoPdLeft": null,
      "MonoPdRight": null,
      "NearPd": 57.7,
      "NearMonoPdLeft": null,
      "NearMonoPdRight": null,
      "FhFrameLeft": null,
      "FhFrameRight": null,
      "FhBoxLeft": null,
      "FhBoxRight": null,
      "Dbl": null,
      "HBox": null,
      "VBox": null,
      "Pano": null,
      "EdRx": null,
      "EdStock": null,
      "Bvd": null,
      "Panto": null,
      "Pd_Modified": 61.9,
      "MonoPdLeft_Modified": null,
      "MonoPdRight_Modified": null,
      "NearPd_Modified": 57.7,
      "NearMonoPdLeft_Modified": null,
      "NearMonoPdRight_Modified": null,
      "FhFrameLeft_Modified": null,
      "FhFrameRight_Modified": null,
      "FhBoxLeft_Modified": null,
      "FhBoxRight_Modified": null,
      "Dbl_Modified": null,
      "HBox_Modified": null,
      "VBox_Modified": null,
      "Pano_Modified": null,
      "EdRx_Modified": null,
      "EdStock_Modified": null,
      "Bvd_Modified": null,
      "Panto_Modified": null,
      "FrameTypeId": 0
    }
  },
  "CalculatedPoints": {
    "left_dbl": [
      null,
      null
    ],
    "right_dbl": [
      null,
      null
    ],
    "left_fh": [
      null,
      null
    ],
    "right_fh": [
      null,
      null
    ],
    "left_a": [
      null,
      null
    ],
    "right_a": [
      null,
      null
    ],
    "left_b_bottom": [
      null,
      null
    ],
    "right_b_bottom": [
      null,
      null
    ],
    "left_b_top": [
      null,
      null
    ],
    "right_b_top": [
      null,
      null
    ],
    "left_pupil": [
      null,
      null
    ],
    "right_pupil": [
      null,
      null
    ]
  }
}