{"Images":["Data\\20231111_194058_542cfa56_IR_LEFT.png","Data\\20231111_194058_542cfa56_IR_RIGHT.png"],"SessionID":"20231111_194058_542cfa56","Id":12834,"Distance":594.673,"Stage":5,"ModifiedData":"2023-11-11T19:40:58.0554721","Country":"Italy","SparkUser":"a****i@g****l.com","DeviceSerialNumber":"SP4-0322-0880","SparkMeasurementId":205,"State":"","CustomerId":"002257","UID":"542cfa56-04a3-40b1-8d74-34d97d7f6bdc","MeasurementData":{"Id":12810,"MeasurementId":12834,"Pd":66,"MonoPdLeft":33,"MonoPdRight":33,"NearPd":62,"NearMonoPdLeft":31,"NearMonoPdRight":31,"FhFrameLeft":24,"FhFrameRight":24.5,"FhBoxLeft":25,"FhBoxRight":25,"Dbl":16,"HBox":51.5,"VBox":42.5,"Pano":7,"EdRx":55.5,"EdStock":55.5,"Bvd":12.5,"Panto":-0.5,"Pd_Modified":66,"MonoPdLeft_Modified":33,"MonoPdRight_Modified":33,"NearPd_Modified":62,"NearMonoPdLeft_Modified":31,"NearMonoPdRight_Modified":31,"FhFrameLeft_Modified":24,"FhFrameRight_Modified":24.5,"FhBoxLeft_Modified":25,"FhBoxRight_Modified":25,"Dbl_Modified":16,"HBox_Modified":51.5,"VBox_Modified":42.5,"Pano_Modified":7,"EdRx_Modified":55.5,"EdStock_Modified":55.5,"Bvd_Modified":12.5,"Panto_Modified":-0.5,"FrameTypeId":0},"MeasurementPoints":{"Id":12805,"MeasurementId":12834,"LeftCamRightDBL":"1031.909,1161.992","LeftCamLeftDBL":"1152.47,1157.969","LeftCamRightFH":"833.216,1358.189","LeftCamLeftFH":"1342.483,1350.142","LeftCamLeftPanto":"1348.233,1030.167","LeftCamLeftA":"1550.897,1135.842","LeftCamRightA":"627.448,1149.923","LeftBottomB":"1370.794,1354.165","LeftTopB":"1382.863,1028.155","RightCamRightDBL":"855.329,1143.858","RightCamLeftDBL":"1330.313,1171.299","RightCamRightFH":"880.414,1508.1","RightCamLeftFH":"1380.495,1512.729","RightCamLeftPanto":"1374.974,1205.8","RightCamLeftA":"1734.374,1147.204","RightCamRightA":"468.255,1129.947"},"MeasurementPupilData":{"Id":12812,"MeasurementId":12834,"Left_LeftPupil_X":917.673,"Left_LeftPupil_Y":836.666,"Left_RightPupil_X":615.093,"Left_RightPupil_Y":835.251,"Left_LeftConfidence":0.969,"Left_RightConfidence":0.941,"Right_LeftPupil_Y":807.704,"Right_RightPupil_Y":804.045,"Right_LeftPupil_X":794.319,"Right_RightPupil_X":504.948,"Right_LeftConfidence":0.953,"Right_RightConfidence":0.924,"RightConfidence_Overall":0.782,"LeftConfidence_Overall":0.849,"Left_LeftPupil_X_Modified":917.673,"Left_LeftPupil_Y_Modified":836.666,"Left_RightPupil_X_Modified":615.093,"Left_RightPupil_Y_Modified":835.251,"Right_LeftPupil_Y_Modified":807.704,"Right_RightPupil_Y_Modified":804.045,"Right_LeftPupil_X_Modified":794.319,"Right_RightPupil_X_Modified":504.948}}