{
  "version": "5.0.2",
  "flags": {
    "sunglasses": true,
    "half rim": false,
    "rimless": false,
    "mask": false,
    "dark skin": false
  },
  "shapes": [
    {
      "label": "iris",
      "points": [
        [
          513.8,
          759.2
        ],
        [
          512.9,
          761.6
        ],
        [
          511.9,
          764.1
        ],
        [
          511.2,
          767.6
        ],
        [
          510.7,
          771.3
        ],
        [
          510.8,
          776.1
        ],
        [
          511.3,
          780.1
        ],
        [
          512.7,
          784.2
        ],
        [
          514.8,
          787.9
        ],
        [
          518,
          791.5
        ],
        [
          521.8,
          794.5
        ],
        [
          525.6,
          796.6
        ],
        [
          529.7,
          798.1
        ],
        [
          533.9,
          799.1
        ],
        [
          538.6,
          799.5
        ],
        [
          542.9,
          799.6
        ],
        [
          548,
          798.9
        ],
        [
          552.7,
          797.4
        ],
        [
          556.4,
          795.6
        ],
        [
          559.2,
          793.9
        ],
        [
          561.6,
          792
        ],
        [
          563.4,
          789.9
        ],
        [
          565,
          787.7
        ],
        [
          566.3,
          785.9
        ],
        [
          567.6,
          783.4
        ],
        [
          568.7,
          780.5
        ],
        [
          569.5,
          778
        ],
        [
          570,
          774.9
        ],
        [
          570.1,
          771.7
        ],
        [
          569.9,
          768.6
        ],
        [
          569.5,
          766.2
        ],
        [
          569.1,
          763.5
        ],
        [
          568.2,
          760.7
        ],
        [
          567.3,
          758.4
        ],
        [
          566,
          756.2
        ],
        [
          564.7,
          754.5
        ],
        [
          562.7,
          752.5
        ],
        [
          560.6,
          750.8
        ],
        [
          557.7,
          748.9
        ],
        [
          554.7,
          747.3
        ],
        [
          551.5,
          745.9
        ],
        [
          547.9,
          745.1
        ],
        [
          543.9,
          744.6
        ],
        [
          539.9,
          744.6
        ],
        [
          536.6,
          744.8
        ],
        [
          533.4,
          745.3
        ],
        [
          530.5,
          746
        ],
        [
          527.2,
          747.1
        ],
        [
          524.2,
          748.4
        ],
        [
          521.1,
          750.3
        ],
        [
          518.7,
          752.3
        ],
        [
          516.9,
          754.4
        ],
        [
          515,
          757.1
        ]
      ],
      "group_id": null,
      "shape_type": "polygon",
      "flags": {}
    },
    {
      "label": "pupil",
      "points": [
        [
          539.8,
          761.9
        ],
        [
          538,
          762
        ],
        [
          535.9,
          762.6
        ],
        [
          534,
          763.7
        ],
        [
          532.6,
          765.1
        ],
        [
          531.4,
          766.4
        ],
        [
          530.5,
          768.3
        ],
        [
          529.9,
          770.3
        ],
        [
          529.6,
          772
        ],
        [
          529.6,
          774
        ],
        [
          529.8,
          776.1
        ],
        [
          530.4,
          777.7
        ],
        [
          531.2,
          779.6
        ],
        [
          532.1,
          780.9
        ],
        [
          533.6,
          782.3
        ],
        [
          535.3,
          783.3
        ],
        [
          537.6,
          783.9
        ],
        [
          540.2,
          784.2
        ],
        [
          542.6,
          784
        ],
        [
          545,
          783.4
        ],
        [
          547,
          782.4
        ],
        [
          548.5,
          781.1
        ],
        [
          549.7,
          779.2
        ],
        [
          550.5,
          776.8
        ],
        [
          550.9,
          774.5
        ],
        [
          551,
          771.7
        ],
        [
          550.7,
          769.5
        ],
        [
          549.6,
          766.9
        ],
        [
          548.6,
          765.1
        ],
        [
          547.1,
          763.8
        ],
        [
          545.6,
          762.8
        ],
        [
          543.9,
          762.2
        ],
        [
          542,
          761.9
        ]
      ],
      "group_id": null,
      "shape_type": "polygon",
      "flags": {}
    },
    {
      "label": "pupil",
      "points": [
        [
          846.8,
          758.1
        ],
        [
          844.6,
          758.5
        ],
        [
          842.8,
          759.4
        ],
        [
          840.9,
          760.5
        ],
        [
          839.4,
          761.8
        ],
        [
          838.3,
          763.2
        ],
        [
          837.4,
          765.1
        ],
        [
          836.8,
          767.1
        ],
        [
          836.5,
          768.8
        ],
        [
          836.5,
          770.8
        ],
        [
          836.7,
          772.9
        ],
        [
          837.3,
          774.5
        ],
        [
          838.1,
          776.4
        ],
        [
          839,
          777.7
        ],
        [
          840.5,
          779.1
        ],
        [
          842.2,
          780.1
        ],
        [
          844.2,
          781
        ],
        [
          846.8,
          781.4
        ],
        [
          849.1,
          781.5
        ],
        [
          851.4,
          781.2
        ],
        [
          853.5,
          780.6
        ],
        [
          855.3,
          779.7
        ],
        [
          856.9,
          778.5
        ],
        [
          858,
          777
        ],
        [
          859,
          775.3
        ],
        [
          859.4,
          773
        ],
        [
          859.3,
          770.7
        ],
        [
          859.1,
          768.5
        ],
        [
          858.3,
          765.8
        ],
        [
          857.1,
          763.5
        ],
        [
          855.8,
          761.7
        ],
        [
          854.5,
          760.3
        ],
        [
          852.8,
          759.1
        ],
        [
          850.9,
          758.4
        ],
        [
          848.7,
          758.1
        ]
      ],
      "group_id": null,
      "shape_type": "polygon",
      "flags": {}
    },
    {
      "label": "iris",
      "points": [
        [
          823,
          757.2
        ],
        [
          821.7,
          759.6
        ],
        [
          820.8,
          762.4
        ],
        [
          820,
          765.7
        ],
        [
          819.6,
          769.4
        ],
        [
          819.9,
          774
        ],
        [
          820.8,
          778.4
        ],
        [
          822.5,
          782.7
        ],
        [
          824.8,
          786.2
        ],
        [
          827.8,
          789.6
        ],
        [
          831.8,
          792.6
        ],
        [
          835.6,
          794.7
        ],
        [
          839.7,
          796.2
        ],
        [
          843.9,
          797.2
        ],
        [
          848.6,
          797.6
        ],
        [
          852.9,
          797.7
        ],
        [
          858,
          797
        ],
        [
          862.7,
          795.5
        ],
        [
          866.4,
          793.7
        ],
        [
          869.2,
          791.9
        ],
        [
          871.6,
          790
        ],
        [
          873.4,
          787.9
        ],
        [
          875,
          785.7
        ],
        [
          876.3,
          783.9
        ],
        [
          877.6,
          781.4
        ],
        [
          878.7,
          778.6
        ],
        [
          879.5,
          776.1
        ],
        [
          880,
          773
        ],
        [
          880.1,
          769.8
        ],
        [
          879.9,
          766.7
        ],
        [
          879.5,
          764.3
        ],
        [
          879.1,
          761.6
        ],
        [
          878.2,
          758.8
        ],
        [
          877.3,
          756.4
        ],
        [
          876,
          754.2
        ],
        [
          874.7,
          752.5
        ],
        [
          872.7,
          750.5
        ],
        [
          870.6,
          748.8
        ],
        [
          867.7,
          746.9
        ],
        [
          864.7,
          745.3
        ],
        [
          861.5,
          744
        ],
        [
          857.9,
          743.2
        ],
        [
          853.9,
          742.7
        ],
        [
          849.9,
          742.7
        ],
        [
          846.6,
          742.9
        ],
        [
          843.4,
          743.4
        ],
        [
          840.5,
          744.1
        ],
        [
          837.2,
          745.2
        ],
        [
          834.2,
          746.4
        ],
        [
          831.1,
          748.3
        ],
        [
          828.5,
          750.3
        ],
        [
          826.3,
          752.4
        ],
        [
          824.4,
          755
        ]
      ],
      "group_id": null,
      "shape_type": "polygon",
      "flags": {}
    }
  ],
  "imagePath": "20231109_145232_2b20f9c9_IR_LEFT.png",
  "imageData": null,
  "imageHeight": 1600,
  "imageWidth": 1300,
  "annotator": "Daria",
  "MetaData": {
    "SessionID": "20231109_145232_2b20f9c9",
    "Id": 12714,
    "Distance": 524.947,
    "Stage": 2,
    "ModifiedData": "2023-11-09T14:52:32.2994999",
    "Country": "Italy",
    "SparkUser": "s****a@l****a.com",
    "DeviceSerialNumber": "SP4-0322-0754",
    "SparkMeasurementId": 2209,
    "State": "",
    "CustomerId": "",
    "UID": "2b20f9c9-1aa7-491a-bdce-8ca199819a61",
    "MeasurementData": {
      "Id": 12690,
      "MeasurementId": 12714,
      "Pd": 61.9,
      "MonoPdLeft": null,
      "MonoPdRight": null,
      "NearPd": 57.7,
      "NearMonoPdLeft": null,
      "NearMonoPdRight": null,
      "FhFrameLeft": null,
      "FhFrameRight": null,
      "FhBoxLeft": null,
      "FhBoxRight": null,
      "Dbl": null,
      "HBox": null,
      "VBox": null,
      "Pano": null,
      "EdRx": null,
      "EdStock": null,
      "Bvd": null,
      "Panto": null,
      "Pd_Modified": 61.9,
      "MonoPdLeft_Modified": null,
      "MonoPdRight_Modified": null,
      "NearPd_Modified": 57.7,
      "NearMonoPdLeft_Modified": null,
      "NearMonoPdRight_Modified": null,
      "FhFrameLeft_Modified": null,
      "FhFrameRight_Modified": null,
      "FhBoxLeft_Modified": null,
      "FhBoxRight_Modified": null,
      "Dbl_Modified": null,
      "HBox_Modified": null,
      "VBox_Modified": null,
      "Pano_Modified": null,
      "EdRx_Modified": null,
      "EdStock_Modified": null,
      "Bvd_Modified": null,
      "Panto_Modified": null,
      "FrameTypeId": 0
    }
  },
  "CalculatedPoints": {
    "left_dbl": [
      null,
      null
    ],
    "right_dbl": [
      null,
      null
    ],
    "left_fh": [
      null,
      null
    ],
    "right_fh": [
      null,
      null
    ],
    "left_a": [
      null,
      null
    ],
    "right_a": [
      null,
      null
    ],
    "left_b_bottom": [
      null,
      null
    ],
    "right_b_bottom": [
      null,
      null
    ],
    "left_b_top": [
      null,
      null
    ],
    "right_b_top": [
      null,
      null
    ],
    "left_pupil": [
      null,
      null
    ],
    "right_pupil": [
      null,
      null
    ]
  }
}