{"Images":["Data\\20231111_125922_1963c1c5_IR_LEFT.png","Data\\20231111_125922_1963c1c5_IR_RIGHT.png"],"SessionID":"20231111_125922_1963c1c5","Id":12837,"Distance":599.093,"Stage":5,"ModifiedData":"2023-11-11T12:59:22.1833862","Country":"Greece","SparkUser":"a****5@g****l.com","DeviceSerialNumber":"SP4-0322-0037","SparkMeasurementId":75,"State":"","CustomerId":"10298","UID":"1963c1c5-5888-4047-b280-b6ca86453170","MeasurementData":{"Id":12813,"MeasurementId":12837,"Pd":63,"MonoPdLeft":30.5,"MonoPdRight":32.5,"NearPd":59,"NearMonoPdLeft":28.5,"NearMonoPdRight":30.5,"FhFrameLeft":31,"FhFrameRight":26,"FhBoxLeft":31,"FhBoxRight":26,"Dbl":20.5,"HBox":50.5,"VBox":43.5,"Pano":-2,"EdRx":54.5,"EdStock":64,"Bvd":17,"Panto":1.5,"Pd_Modified":63,"MonoPdLeft_Modified":30.5,"MonoPdRight_Modified":32.5,"NearPd_Modified":59,"NearMonoPdLeft_Modified":28.5,"NearMonoPdRight_Modified":30.5,"FhFrameLeft_Modified":31,"FhFrameRight_Modified":26,"FhBoxLeft_Modified":31,"FhBoxRight_Modified":26,"Dbl_Modified":20.5,"HBox_Modified":50.5,"VBox_Modified":43.5,"Pano_Modified":-2,"EdRx_Modified":54.5,"EdStock_Modified":64,"Bvd_Modified":17,"Panto_Modified":1.5,"FrameTypeId":1},"MeasurementPoints":{"Id":12808,"MeasurementId":12837,"LeftCamRightDBL":"751.389,1367.486","LeftCamLeftDBL":"909.223,1373.627","LeftCamRightFH":"592.858,1561.861","LeftCamLeftFH":"1073.567,1558.187","LeftCamLeftPanto":"1049.978,1244.916","LeftCamLeftA":"1303.186,1346.549","LeftCamRightA":"350.021,1367.723","LeftBottomB":"1093.92,1558.187","LeftTopB":"1113.329,1229.036","RightCamRightDBL":"730.829,1335.329","RightCamLeftDBL":"1092.979,1362.556","RightCamRightFH":"579.57,1714.824","RightCamLeftFH":"1061.342,1715.734","RightCamLeftPanto":"1032.615,1397.126","RightCamLeftA":"1461.921,1333.944","RightCamRightA":"357.297,1340.651"},"MeasurementPupilData":{"Id":12815,"MeasurementId":12837,"Left_LeftPupil_X":732.26,"Left_LeftPupil_Y":950.767,"Left_RightPupil_X":451.187,"Left_RightPupil_Y":973.959,"Left_LeftConfidence":0.953,"Left_RightConfidence":0.941,"Right_LeftPupil_Y":917.617,"Right_RightPupil_Y":942.55,"Right_LeftPupil_X":645.577,"Right_RightPupil_X":361.881,"Right_LeftConfidence":0.939,"Right_RightConfidence":0.961,"RightConfidence_Overall":0.864,"LeftConfidence_Overall":0.8,"Left_LeftPupil_X_Modified":732.26,"Left_LeftPupil_Y_Modified":950.767,"Left_RightPupil_X_Modified":451.187,"Left_RightPupil_Y_Modified":973.959,"Right_LeftPupil_Y_Modified":917.617,"Right_RightPupil_Y_Modified":942.55,"Right_LeftPupil_X_Modified":645.577,"Right_RightPupil_X_Modified":361.881}}