{
  "version": "5.0.2",
  "flags": {
    "sunglasses": true,
    "half rim": false,
    "rimless": false,
    "mask": false,
    "dark skin": false
  },
  "shapes": [
    {
      "label": "pupil",
      "points": [
        [
          838.1,
          762.3
        ],
        [
          836,
          762.4
        ],
        [
          834,
          762.8
        ],
        [
          832.1,
          763.7
        ],
        [
          830.1,
          765.2
        ],
        [
          828.7,
          766.8
        ],
        [
          827.6,
          768.9
        ],
        [
          826.9,
          771.4
        ],
        [
          826.8,
          773.8
        ],
        [
          827.1,
          776.5
        ],
        [
          827.8,
          778.6
        ],
        [
          829.2,
          780.5
        ],
        [
          830.7,
          781.8
        ],
        [
          832.7,
          782.8
        ],
        [
          835,
          783.4
        ],
        [
          837.1,
          783.4
        ],
        [
          839.7,
          783
        ],
        [
          841.7,
          782.3
        ],
        [
          843.6,
          781.3
        ],
        [
          845.5,
          779.8
        ],
        [
          846.7,
          778.4
        ],
        [
          847.6,
          776.9
        ],
        [
          848.1,
          775.7
        ],
        [
          848.4,
          773.8
        ],
        [
          848.4,
          771.7
        ],
        [
          847.9,
          769.3
        ],
        [
          847,
          767.4
        ],
        [
          845.7,
          765.5
        ],
        [
          844,
          764.1
        ],
        [
          842.1,
          763.1
        ],
        [
          840.1,
          762.5
        ]
      ],
      "group_id": null,
      "shape_type": "polygon",
      "flags": {}
    },
    {
      "label": "pupil",
      "points": [
        [
          502.9,
          766
        ],
        [
          500.8,
          766.1
        ],
        [
          498.8,
          766.5
        ],
        [
          496.9,
          767.4
        ],
        [
          494.9,
          768.9
        ],
        [
          493.5,
          770.4
        ],
        [
          492.4,
          772.5
        ],
        [
          491.7,
          775
        ],
        [
          491.6,
          777.4
        ],
        [
          491.9,
          780.1
        ],
        [
          492.6,
          782.2
        ],
        [
          494,
          784.1
        ],
        [
          495.5,
          785.5
        ],
        [
          497.5,
          786.5
        ],
        [
          499.8,
          787.1
        ],
        [
          501.9,
          787.1
        ],
        [
          504.5,
          786.7
        ],
        [
          506.5,
          785.9
        ],
        [
          508.4,
          784.9
        ],
        [
          510.3,
          783.4
        ],
        [
          511.7,
          781.7
        ],
        [
          512.5,
          780.4
        ],
        [
          513,
          779.1
        ],
        [
          513.4,
          777.4
        ],
        [
          513.2,
          775.3
        ],
        [
          512.8,
          772.9
        ],
        [
          511.8,
          771.1
        ],
        [
          510.3,
          769.4
        ],
        [
          508.6,
          768
        ],
        [
          506.9,
          766.9
        ],
        [
          504.9,
          766.2
        ]
      ],
      "group_id": null,
      "shape_type": "polygon",
      "flags": {}
    },
    {
      "label": "iris",
      "points": [
        [
          811.7,
          763.7
        ],
        [
          810.7,
          766.1
        ],
        [
          810.2,
          768.2
        ],
        [
          809.5,
          771.5
        ],
        [
          809.3,
          775.3
        ],
        [
          809.5,
          779.7
        ],
        [
          810.2,
          783.9
        ],
        [
          811.4,
          787.6
        ],
        [
          813.9,
          791.3
        ],
        [
          816.7,
          794.6
        ],
        [
          820,
          797.4
        ],
        [
          823.2,
          799.3
        ],
        [
          826.4,
          800.7
        ],
        [
          830.8,
          801.8
        ],
        [
          835,
          802.4
        ],
        [
          839.9,
          802.3
        ],
        [
          844.5,
          801.9
        ],
        [
          849.3,
          801
        ],
        [
          853.5,
          799.3
        ],
        [
          856.6,
          797.5
        ],
        [
          859.8,
          794.6
        ],
        [
          862.4,
          790.9
        ],
        [
          864.8,
          786.5
        ],
        [
          866.3,
          781.4
        ],
        [
          866.7,
          776.8
        ],
        [
          866.7,
          771.8
        ],
        [
          865.9,
          767.2
        ],
        [
          864.9,
          763.9
        ],
        [
          863.5,
          760.6
        ],
        [
          862.3,
          758.7
        ],
        [
          860.6,
          756.5
        ],
        [
          858.9,
          754.6
        ],
        [
          856.4,
          752.9
        ],
        [
          853.7,
          751.6
        ],
        [
          850.9,
          750.4
        ],
        [
          847.5,
          749.6
        ],
        [
          844.1,
          749
        ],
        [
          841.2,
          748.7
        ],
        [
          838,
          748.6
        ],
        [
          835.2,
          748.7
        ],
        [
          832.3,
          749.2
        ],
        [
          829.4,
          749.9
        ],
        [
          825.8,
          751
        ],
        [
          822.9,
          752.4
        ],
        [
          819.6,
          754.3
        ],
        [
          817.3,
          756.1
        ],
        [
          815.3,
          758.2
        ],
        [
          813.4,
          761
        ]
      ],
      "group_id": null,
      "shape_type": "polygon",
      "flags": {}
    },
    {
      "label": "iris",
      "points": [
        [
          476.2,
          765.3
        ],
        [
          475.4,
          767.7
        ],
        [
          474.7,
          769.8
        ],
        [
          474,
          773
        ],
        [
          473.5,
          776.9
        ],
        [
          473.7,
          781.3
        ],
        [
          474.4,
          785.5
        ],
        [
          475.6,
          789.2
        ],
        [
          478,
          792.9
        ],
        [
          480.8,
          796.2
        ],
        [
          484.1,
          799
        ],
        [
          487.3,
          800.9
        ],
        [
          490.5,
          802.3
        ],
        [
          494.9,
          803.4
        ],
        [
          499.1,
          804
        ],
        [
          504,
          803.9
        ],
        [
          508.6,
          803.5
        ],
        [
          513.4,
          802.6
        ],
        [
          517.6,
          800.9
        ],
        [
          520.7,
          799.1
        ],
        [
          523.9,
          796.2
        ],
        [
          526.5,
          792.5
        ],
        [
          528.9,
          788.1
        ],
        [
          530.4,
          783
        ],
        [
          530.9,
          778.4
        ],
        [
          530.8,
          773.4
        ],
        [
          530,
          768.8
        ],
        [
          529,
          765.5
        ],
        [
          527.6,
          762.2
        ],
        [
          526.4,
          760.3
        ],
        [
          524.7,
          758.1
        ],
        [
          523,
          756.2
        ],
        [
          520.5,
          754.5
        ],
        [
          517.8,
          753.2
        ],
        [
          515,
          752
        ],
        [
          511.6,
          751.2
        ],
        [
          508.2,
          750.6
        ],
        [
          505.3,
          750.3
        ],
        [
          502.1,
          750.2
        ],
        [
          499.3,
          750.3
        ],
        [
          496.4,
          750.8
        ],
        [
          493.6,
          751.5
        ],
        [
          490,
          752.6
        ],
        [
          487.1,
          754
        ],
        [
          483.8,
          755.9
        ],
        [
          481.5,
          757.7
        ],
        [
          479.5,
          759.8
        ],
        [
          477.6,
          762.6
        ]
      ],
      "group_id": null,
      "shape_type": "polygon",
      "flags": {}
    }
  ],
  "imagePath": "20231109_110934_1ff01eb5_IR_RIGHT.png",
  "imageData": null,
  "imageHeight": 1600,
  "imageWidth": 1300,
  "annotator": "Anna",
  "MetaData": {
    "SessionID": "20231109_110934_1ff01eb5",
    "Id": 12658,
    "Distance": 535.958,
    "Stage": 5,
    "ModifiedData": "2023-11-09T11:09:34.9831624",
    "Country": "Portugal",
    "SparkUser": "m****a@s****o.pt",
    "DeviceSerialNumber": "SP4-0322-0826",
    "SparkMeasurementId": 63,
    "State": "",
    "CustomerId": "395",
    "UID": "1ff01eb5-6a08-4987-9c8c-b6b3d3fdbfce",
    "MeasurementData": {
      "Id": 12634,
      "MeasurementId": 12658,
      "Pd": 68.5,
      "MonoPdLeft": 33.5,
      "MonoPdRight": 35,
      "NearPd": 63.5,
      "NearMonoPdLeft": 31,
      "NearMonoPdRight": 32.5,
      "FhFrameLeft": 23.5,
      "FhFrameRight": 23.5,
      "FhBoxLeft": 24,
      "FhBoxRight": 24,
      "Dbl": 19,
      "HBox": 53,
      "VBox": 35.5,
      "Pano": 6,
      "EdRx": 57,
      "EdStock": 59.5,
      "Bvd": 12.5,
      "Panto": 1,
      "Pd_Modified": 68.5,
      "MonoPdLeft_Modified": 33.5,
      "MonoPdRight_Modified": 35,
      "NearPd_Modified": 63.5,
      "NearMonoPdLeft_Modified": 31,
      "NearMonoPdRight_Modified": 32.5,
      "FhFrameLeft_Modified": 23.5,
      "FhFrameRight_Modified": 23.5,
      "FhBoxLeft_Modified": 24,
      "FhBoxRight_Modified": 24,
      "Dbl_Modified": 19,
      "HBox_Modified": 53,
      "VBox_Modified": 35.5,
      "Pano_Modified": 6,
      "EdRx_Modified": 57,
      "EdStock_Modified": 59.5,
      "Bvd_Modified": 12.5,
      "Panto_Modified": 1,
      "FrameTypeId": 0
    }
  },
  "CalculatedPoints": {
    "left_dbl": [
      null,
      null
    ],
    "right_dbl": [
      null,
      null
    ],
    "left_fh": [
      null,
      null
    ],
    "right_fh": [
      null,
      null
    ],
    "left_a": [
      null,
      null
    ],
    "right_a": [
      null,
      null
    ],
    "left_b_bottom": [
      null,
      null
    ],
    "right_b_bottom": [
      null,
      null
    ],
    "left_b_top": [
      null,
      null
    ],
    "right_b_top": [
      null,
      null
    ],
    "left_pupil": [
      null,
      null
    ],
    "right_pupil": [
      null,
      null
    ]
  }
}